little_mallet_wrapper/__init__.py
little_mallet_wrapper/little_mallet_wrapper.py
little_mallet_wrapper-0.5.0.dist-info/LICENSE
little_mallet_wrapper-0.5.0.dist-info/METADATA
little_mallet_wrapper-0.5.0.dist-info/WHEEL
little_mallet_wrapper-0.5.0.dist-info/top_level.txt
little_mallet_wrapper-0.5.0.dist-info/RECORD
